<?xml version="1.0" encoding="UTF-8"?>
<!DOCTYPE hibernate-mapping PUBLIC
        "-//Hibernate/Hibernate Mapping DTD 3.0//EN"
        "http://www.hibernate.org/dtd/hibernate-mapping-3.0.dtd">
<hibernate-mapping package="com.qwm.ssh_crm.domain">
    <class name="SaleVisit" table="cst_salevisit">
        <id name="visit_id">
            <generator class="uuid"></generator>
        </id>

        <property name="visit_interviewee"></property>
        <property name="visit_addr"></property>
        <property name="visit_detail"></property>
        <property name="visit_time"></property>
        <property name="visit_nexttime"></property>

        <many-to-one name="customer" column="visit_cust_id" class="Customer"/>
        <many-to-one name="user" column="visit_user_id" class="User"/>

    </class>
</hibernate-mapping>